livekit/plugins/__init__.py
livekit/plugins/marbert/__init__.py
livekit/plugins/marbert/turn_detector.py
livekit/plugins/marbert/version.py
livekit_plugins_marbert-0.1.1.dist-info/METADATA
livekit_plugins_marbert-0.1.1.dist-info/WHEEL
livekit_plugins_marbert-0.1.1.dist-info/top_level.txt
livekit_plugins_marbert-0.1.1.dist-info/RECORD
