Metadata-Version: 2.4
Name: livekit-plugins-marbert
Version: 0.1.1
Summary: Arabic End-of-Utterance detection for LiveKit using MARBERT
Home-page: https://github.com/azeddinshr/livekit-plugins-marbert
Author: Azeddin Sahir
Author-email: azdinsahir11@gmail.com
Keywords: livekit voice-ai arabic eou turn-detection marbert nlp
Classifier: Development Status :: 4 - Beta
Classifier: Intended Audience :: Developers
Classifier: License :: OSI Approved :: Apache Software License
Classifier: Programming Language :: Python :: 3.9
Classifier: Programming Language :: Python :: 3.10
Classifier: Programming Language :: Python :: 3.11
Classifier: Topic :: Software Development :: Libraries
Classifier: Topic :: Scientific/Engineering :: Artificial Intelligence
Requires-Python: >=3.9
Requires-Dist: livekit-agents<2.0.0,>=1.3.9
Requires-Dist: transformers<5.0.0,>=4.30.0
Requires-Dist: torch<3.0.0,>=2.0.0
Requires-Dist: numpy<2.0.0,>=1.21.0
Dynamic: author
Dynamic: author-email
Dynamic: classifier
Dynamic: description
Dynamic: description-content-type
Dynamic: home-page
Dynamic: keywords
Dynamic: requires-dist
Dynamic: requires-python
Dynamic: summary
